Workbook

Sheet Cover
B2: CarbonSmart Solutions Africa - QA Test Cases
B3: Farm ERP + Biochar Carbon-Credit dMRV Platform - v2.0.0
B5: Build under test
B6: Tested by
B7: Cycle / Date
B8: Environment | C8: Client http://localhost:5173 | API http://localhost:3001
B10: How to use | C10: One tab per test area. Fill Status (dropdown), Tester, Date, Defect ID and Comments for each case.
B11: Status values | C11: Pass / Fail / Blocked / N/A (dropdown in each Status cell)
B12: Severity | C12: S1 Critical (blocks release) | S2 Major | S3 Minor | S4 Cosmetic
B13: Setup | C13: cd server; npm run db:push; npm run db:seed; npm run dev + cd client; npm run dev
B14: IMPORTANT | C14: Re-run 'npm run db:seed' between cycles so gate / mass-balance tests start from known data.
B15: Accounts | C15: admin/admin123 | officer/officer123 | lab/lab123 | auditor/auditor123 | farmer/farmer123 (all @carbonsmart.co.za)
B16: Full detail | C16: See QA_TEST_PLAN.md for setup, gate cheat-sheet, E2E narrative and known limitations.
B18: Totals
B19: Area | C19: Cases | D19: Pass | E19: Fail | F19: Blocked | G19: Not run
B20: Auth & Session | C20: 12 | D20: =COUNTIF('Auth & Session'!F2:F13,"Pass") | E20: =COUNTIF('Auth & Session'!F2:F13,"Fail") | F20: =COUNTIF('Auth & Session'!F2:F13,"Blocked") | G20: =12-COUNTIF('Auth & Session'!F2:F13,"Pass")-COUNTIF('Auth & Session'!F2:F13,"Fail")-COUNTIF('Auth & Session'!F2:F13,"Blocked")-COUNTIF('Auth & Session'!F2:F13,"N/A")
B21: RBAC | C21: 11 | D21: =COUNTIF('RBAC'!F2:F12,"Pass") | E21: =COUNTIF('RBAC'!F2:F12,"Fail") | F21: =COUNTIF('RBAC'!F2:F12,"Blocked") | G21: =11-COUNTIF('RBAC'!F2:F12,"Pass")-COUNTIF('RBAC'!F2:F12,"Fail")-COUNTIF('RBAC'!F2:F12,"Blocked")-COUNTIF('RBAC'!F2:F12,"N/A")
B22: Farmer Mgmt | C22: 7 | D22: =COUNTIF('Farmer Mgmt'!F2:F8,"Pass") | E22: =COUNTIF('Farmer Mgmt'!F2:F8,"Fail") | F22: =COUNTIF('Farmer Mgmt'!F2:F8,"Blocked") | G22: =7-COUNTIF('Farmer Mgmt'!F2:F8,"Pass")-COUNTIF('Farmer Mgmt'!F2:F8,"Fail")-COUNTIF('Farmer Mgmt'!F2:F8,"Blocked")-COUNTIF('Farmer Mgmt'!F2:F8,"N/A")
B23: Biochar + Gate1 | C23: 11 | D23: =COUNTIF('Biochar + Gate1'!F2:F12,"Pass") | E23: =COUNTIF('Biochar + Gate1'!F2:F12,"Fail") | F23: =COUNTIF('Biochar + Gate1'!F2:F12,"Blocked") | G23: =11-COUNTIF('Biochar + Gate1'!F2:F12,"Pass")-COUNTIF('Biochar + Gate1'!F2:F12,"Fail")-COUNTIF('Biochar + Gate1'!F2:F12,"Blocked")-COUNTIF('Biochar + Gate1'!F2:F12,"N/A")
B24: dCoC + Evidence | C24: 8 | D24: =COUNTIF('dCoC + Evidence'!F2:F9,"Pass") | E24: =COUNTIF('dCoC + Evidence'!F2:F9,"Fail") | F24: =COUNTIF('dCoC + Evidence'!F2:F9,"Blocked") | G24: =8-COUNTIF('dCoC + Evidence'!F2:F9,"Pass")-COUNTIF('dCoC + Evidence'!F2:F9,"Fail")-COUNTIF('dCoC + Evidence'!F2:F9,"Blocked")-COUNTIF('dCoC + Evidence'!F2:F9,"N/A")
B25: Lab + Gate3 | C25: 10 | D25: =COUNTIF('Lab + Gate3'!F2:F11,"Pass") | E25: =COUNTIF('Lab + Gate3'!F2:F11,"Fail") | F25: =COUNTIF('Lab + Gate3'!F2:F11,"Blocked") | G25: =10-COUNTIF('Lab + Gate3'!F2:F11,"Pass")-COUNTIF('Lab + Gate3'!F2:F11,"Fail")-COUNTIF('Lab + Gate3'!F2:F11,"Blocked")-COUNTIF('Lab + Gate3'!F2:F11,"N/A")
B26: Camera Log | C26: 4 | D26: =COUNTIF('Camera Log'!F2:F5,"Pass") | E26: =COUNTIF('Camera Log'!F2:F5,"Fail") | F26: =COUNTIF('Camera Log'!F2:F5,"Blocked") | G26: =4-COUNTIF('Camera Log'!F2:F5,"Pass")-COUNTIF('Camera Log'!F2:F5,"Fail")-COUNTIF('Camera Log'!F2:F5,"Blocked")-COUNTIF('Camera Log'!F2:F5,"N/A")
B27: Yield + Gate2 | C27: 6 | D27: =COUNTIF('Yield + Gate2'!F2:F7,"Pass") | E27: =COUNTIF('Yield + Gate2'!F2:F7,"Fail") | F27: =COUNTIF('Yield + Gate2'!F2:F7,"Blocked") | G27: =6-COUNTIF('Yield + Gate2'!F2:F7,"Pass")-COUNTIF('Yield + Gate2'!F2:F7,"Fail")-COUNTIF('Yield + Gate2'!F2:F7,"Blocked")-COUNTIF('Yield + Gate2'!F2:F7,"N/A")
B28: Seasonality | C28: 5 | D28: =COUNTIF('Seasonality'!F2:F6,"Pass") | E28: =COUNTIF('Seasonality'!F2:F6,"Fail") | F28: =COUNTIF('Seasonality'!F2:F6,"Blocked") | G28: =5-COUNTIF('Seasonality'!F2:F6,"Pass")-COUNTIF('Seasonality'!F2:F6,"Fail")-COUNTIF('Seasonality'!F2:F6,"Blocked")-COUNTIF('Seasonality'!F2:F6,"N/A")
B29: Ledger | C29: 5 | D29: =COUNTIF('Ledger'!F2:F6,"Pass") | E29: =COUNTIF('Ledger'!F2:F6,"Fail") | F29: =COUNTIF('Ledger'!F2:F6,"Blocked") | G29: =5-COUNTIF('Ledger'!F2:F6,"Pass")-COUNTIF('Ledger'!F2:F6,"Fail")-COUNTIF('Ledger'!F2:F6,"Blocked")-COUNTIF('Ledger'!F2:F6,"N/A")
B30: Farmer Impact | C30: 12 | D30: =COUNTIF('Farmer Impact'!F2:F13,"Pass") | E30: =COUNTIF('Farmer Impact'!F2:F13,"Fail") | F30: =COUNTIF('Farmer Impact'!F2:F13,"Blocked") | G30: =12-COUNTIF('Farmer Impact'!F2:F13,"Pass")-COUNTIF('Farmer Impact'!F2:F13,"Fail")-COUNTIF('Farmer Impact'!F2:F13,"Blocked")-COUNTIF('Farmer Impact'!F2:F13,"N/A")
B31: Public Passport | C31: 6 | D31: =COUNTIF('Public Passport'!F2:F7,"Pass") | E31: =COUNTIF('Public Passport'!F2:F7,"Fail") | F31: =COUNTIF('Public Passport'!F2:F7,"Blocked") | G31: =6-COUNTIF('Public Passport'!F2:F7,"Pass")-COUNTIF('Public Passport'!F2:F7,"Fail")-COUNTIF('Public Passport'!F2:F7,"Blocked")-COUNTIF('Public Passport'!F2:F7,"N/A")
B32: Carbon + Offline | C32: 5 | D32: =COUNTIF('Carbon + Offline'!F2:F6,"Pass") | E32: =COUNTIF('Carbon + Offline'!F2:F6,"Fail") | F32: =COUNTIF('Carbon + Offline'!F2:F6,"Blocked") | G32: =5-COUNTIF('Carbon + Offline'!F2:F6,"Pass")-COUNTIF('Carbon + Offline'!F2:F6,"Fail")-COUNTIF('Carbon + Offline'!F2:F6,"Blocked")-COUNTIF('Carbon + Offline'!F2:F6,"N/A")
B33: Mapping | C33: 5 | D33: =COUNTIF('Mapping'!F2:F6,"Pass") | E33: =COUNTIF('Mapping'!F2:F6,"Fail") | F33: =COUNTIF('Mapping'!F2:F6,"Blocked") | G33: =5-COUNTIF('Mapping'!F2:F6,"Pass")-COUNTIF('Mapping'!F2:F6,"Fail")-COUNTIF('Mapping'!F2:F6,"Blocked")-COUNTIF('Mapping'!F2:F6,"N/A")
B34: LSM | C34: 3 | D34: =COUNTIF('LSM'!F2:F4,"Pass") | E34: =COUNTIF('LSM'!F2:F4,"Fail") | F34: =COUNTIF('LSM'!F2:F4,"Blocked") | G34: =3-COUNTIF('LSM'!F2:F4,"Pass")-COUNTIF('LSM'!F2:F4,"Fail")-COUNTIF('LSM'!F2:F4,"Blocked")-COUNTIF('LSM'!F2:F4,"N/A")
B35: Smart Farming | C35: 6 | D35: =COUNTIF('Smart Farming'!F2:F7,"Pass") | E35: =COUNTIF('Smart Farming'!F2:F7,"Fail") | F35: =COUNTIF('Smart Farming'!F2:F7,"Blocked") | G35: =6-COUNTIF('Smart Farming'!F2:F7,"Pass")-COUNTIF('Smart Farming'!F2:F7,"Fail")-COUNTIF('Smart Farming'!F2:F7,"Blocked")-COUNTIF('Smart Farming'!F2:F7,"N/A")
B36: Analytics | C36: 5 | D36: =COUNTIF('Analytics'!F2:F6,"Pass") | E36: =COUNTIF('Analytics'!F2:F6,"Fail") | F36: =COUNTIF('Analytics'!F2:F6,"Blocked") | G36: =5-COUNTIF('Analytics'!F2:F6,"Pass")-COUNTIF('Analytics'!F2:F6,"Fail")-COUNTIF('Analytics'!F2:F6,"Blocked")-COUNTIF('Analytics'!F2:F6,"N/A")
B37: Audit Log | C37: 4 | D37: =COUNTIF('Audit Log'!F2:F5,"Pass") | E37: =COUNTIF('Audit Log'!F2:F5,"Fail") | F37: =COUNTIF('Audit Log'!F2:F5,"Blocked") | G37: =4-COUNTIF('Audit Log'!F2:F5,"Pass")-COUNTIF('Audit Log'!F2:F5,"Fail")-COUNTIF('Audit Log'!F2:F5,"Blocked")-COUNTIF('Audit Log'!F2:F5,"N/A")
B38: Non-Functional | C38: 9 | D38: =COUNTIF('Non-Functional'!F2:F10,"Pass") | E38: =COUNTIF('Non-Functional'!F2:F10,"Fail") | F38: =COUNTIF('Non-Functional'!F2:F10,"Blocked") | G38: =9-COUNTIF('Non-Functional'!F2:F10,"Pass")-COUNTIF('Non-Functional'!F2:F10,"Fail")-COUNTIF('Non-Functional'!F2:F10,"Blocked")-COUNTIF('Non-Functional'!F2:F10,"N/A")
B39: E2E Scenario | C39: 13 | D39: =COUNTIF('E2E Scenario'!F2:F14,"Pass") | E39: =COUNTIF('E2E Scenario'!F2:F14,"Fail") | F39: =COUNTIF('E2E Scenario'!F2:F14,"Blocked") | G39: =13-COUNTIF('E2E Scenario'!F2:F14,"Pass")-COUNTIF('E2E Scenario'!F2:F14,"Fail")-COUNTIF('E2E Scenario'!F2:F14,"Blocked")-COUNTIF('E2E Scenario'!F2:F14,"N/A")
B40: TOTAL | C40: =SUM(C20:C39) | D40: =SUM(D20:D39) | E40: =SUM(E20:E39) | F40: =SUM(F20:F39) | G40: =SUM(G20:G39)
B42: 147 test cases across 20 areas

Sheet Auth & Session
A1: Test ID | B1: Test | C1: Steps | D1: Expected Result | E1: Severity | F1: Status | G1: Tester | H1: Date | I1: Defect ID | J1: Comments
A2: TC-AUTH-01 | B2: Valid login (each role) | C2: For each of the 5 accounts: /login, enter creds, Sign In | D2: Redirect to /dashboard (farmer -> farmer view); welcome toast; role-appropriate sidebar | E2: S1
A3: TC-AUTH-02 | B3: Demo autofill | C3: Click a demo-credential row on login page | D3: Email + password auto-populate | E3: S3
A4: TC-AUTH-03 | B4: Invalid password | C4: Correct email, wrong password | D4: Error toast 'Invalid credentials'; stays on login | E4: S2
A5: TC-AUTH-04 | B5: Empty/short fields | C5: Submit blank; password < 6 chars | D5: Inline Zod validation; no request sent | E5: S3
A6: TC-AUTH-05 | B6: Session persists | C6: Log in, refresh browser (F5) | D6: Still authenticated, same page | E6: S2
A7: TC-AUTH-06 | B7: Logout | C7: Click logout in sidebar | D7: Redirect to /login; back-button does not re-enter app | E7: S2
A8: TC-AUTH-07 | B8: Protected route guard | C8: Logged out, visit /dashboard directly | D8: Redirected to /login | E8: S1
A9: TC-AUTH-08 | B9: Token refresh | C9: Log in, idle >15 min, perform an action | D9: Action succeeds (silent refresh), no forced logout | E9: S2
A10: TC-AUTH-09 | B10: Registration (new farmer) | C10: /register -> 3-step wizard -> submit | D10: 201; auto-login; farmer ID CSA-YYYY-NNNNN; dashboard | E10: S1
A11: TC-AUTH-10 | B11: Duplicate email | C11: Register with farmer@carbonsmart.co.za | D11: Error 'Email already registered' (409) | E11: S2
A12: TC-AUTH-11 | B12: Offline login fallback | C12: Stop backend, log in with a demo account | D12: Logs in with '(offline demo mode)' toast | E12: S3
A13: TC-AUTH-12 | B13: Rate limiting | C13: Fire >20 login attempts in 15 min | D13: Later attempts 429 'Too many auth attempts' | E13: S3

Sheet RBAC
A1: Test ID | B1: Test | C1: Steps | D1: Expected Result | E1: Severity | F1: Status | G1: Tester | H1: Date | I1: Defect ID | J1: Comments
A2: TC-RBAC-01 | B2: Admin sees everything | C2: Login admin | D2: Sidebar: Farmers, Carbon, Map, LSM, dMRV Registry (all 6), Lab Portal, Smart Farming, Analytics, Audit Log, Settings | E2: S2
A3: TC-RBAC-02 | B3: Field Officer nav | C3: Login officer | D3: dMRV Registry + Smart Farming; no Audit Log | E3: S2
A4: TC-RBAC-03 | B4: Lab Technician nav | C4: Login lab | D4: Lab Portal; no dMRV Registry or Smart Farming | E4: S2
A5: TC-RBAC-04 | B5: VVB Auditor nav | C5: Login auditor | D5: dMRV Registry + Audit Log; 'Read-only audit access' badge; no create/edit buttons | E5: S1
A6: TC-RBAC-05 | B6: Farmer nav | C6: Login farmer | D6: Dashboard + My Farm Impact + Smart Farming; no dMRV Registry/Audit | E6: S1
A7: TC-RBAC-06 | B7: Auditor write blocked (API) | C7: As auditor, any POST/PATCH via console/curl | D7: 403 'VVB Auditor access is strictly read-only' | E7: S1
A8: TC-RBAC-07 | B8: Farmer cannot create batch | C8: As farmer, POST /api/v1/biochar | D8: 403 Insufficient permissions | E8: S1
A9: TC-RBAC-08 | B9: Officer cannot edit historical batch | C9: As officer, PATCH /api/v1/biochar/:id | D9: 403 (edits admin-only) | E9: S2
A10: TC-RBAC-09 | B10: Officer cannot enter lab results | C10: As officer, POST /api/v1/samples/:id/results | D10: 403 (chemistry lab-owned) | E10: S1
A11: TC-RBAC-10 | B11: Farmer cannot view another farm | C11: As farmer, GET /api/v1/impact/{other-db-id} | D11: 403 'may only view their own dashboard' | E11: S1
A12: TC-RBAC-11 | B12: Audit log admin/auditor only | C12: As farmer/officer, GET /api/v1/audit | D12: 403 | E12: S2

Sheet Farmer Mgmt
A1: Test ID | B1: Test | C1: Steps | D1: Expected Result | E1: Severity | F1: Status | G1: Tester | H1: Date | I1: Defect ID | J1: Comments
A2: TC-FARM-01 | B2: Farmers list loads (live) | C2: Admin -> Farmers | D2: List from API; green 'Live data' badge | E2: S1
A3: TC-FARM-02 | B3: Search | C3: Type name/farm/farmer ID | D3: List filters to matches | E3: S3
A4: TC-FARM-03 | B4: Province & status filter | C4: Apply filters | D4: Only matching rows; reset clears | E4: S3
A5: TC-FARM-04 | B5: Farmer detail | C5: Click a farmer row | D5: Profile, carbon history chart, alerts | E5: S2
A6: TC-FARM-05 | B6: Unique farmer ID format | C6: Inspect / register new | D6: Matches CSA-YYYY-NNNNN; sequential, unique | E6: S2
A7: TC-FARM-06 | B7: Update status | C7: Change status active/inactive/pending | D7: Persists after refresh; toast | E7: S2
A8: TC-FARM-07 | B8: Mock fallback | C8: Stop backend, open Farmers | D8: Renders with 'Demo data' badge (no crash) | E8: S2

Sheet Biochar + Gate1
A1: Test ID | B1: Test | C1: Steps | D1: Expected Result | E1: Severity | F1: Status | G1: Tester | H1: Date | I1: Defect ID | J1: Comments
A2: TC-BIO-01 | B2: Mass-balance cards | C2: Open /dmrv/biochar | D2: 4 cards Produced/Shipped/Applied/Remaining; Produced-Shipped-Applied=Remaining | E2: S1
A3: TC-BIO-02 | B3: Production log table | C3: Open page | D3: BC-2026-001..004 with feedstock badge, temp, weight, region, dCoC, eligibility | E3: S1
A4: TC-BIO-03 | B4: dCoC status colours | C4: Inspect status column | D4: produced=gray, sampled/lab_received=orange, results_entered=green, rejected=red | E4: S3
A5: TC-BIO-04 | B5: GATE 1 - reject <350C | C5: New Production Log, temp 300, submit | D5: BLOCKED; red banner '...minimum of 350C...'; no row created | E5: S1
A6: TC-BIO-05 | B6: Gate 1 - accept >=350C | C6: New Production Log, temp 520, submit | D6: 201; new batch appears; dCoC=Produced; not yet eligible | E6: S1
A7: TC-BIO-06 | B7: Batch number sequence | C7: Create two batches | D7: Numbers increment BC-2026-005, -006 | E7: S3
A8: TC-BIO-07 | B8: Log shipment | C8: Manage modal -> Log Shipment | D8: Shipment added; Remaining decreases | E8: S2
A9: TC-BIO-08 | B9: Mass-balance guard (over-ship) | C9: Ship more than Remaining | D9: 422 'only X t remain...'; nothing saved | E9: S1
A10: TC-BIO-09 | B10: Log application | C10: Manage modal -> Log Application | D10: Application added; Remaining decreases; farmer CO2e reflects | E10: S2
A11: TC-BIO-10 | B11: Over-apply guard | C11: Apply more than Remaining | D11: 422 mass-balance error; nothing saved | E11: S2
A12: TC-BIO-11 | B12: Field validation | C12: Blank/negative weight | D12: Inline validation; request rejected | E12: S3

Sheet dCoC + Evidence
A1: Test ID | B1: Test | C1: Steps | D1: Expected Result | E1: Severity | F1: Status | G1: Tester | H1: Date | I1: Defect ID | J1: Comments
A2: TC-DCOC-01 | B2: Traffic-light legend | C2: Open /dmrv/dcoc | D2: Legend Yellow/Orange/Green/Red explained | E2: S3
A3: TC-DCOC-02 | B3: Status counts | C3: Open page | D3: Count cards match table totals | E3: S3
A4: TC-DCOC-03 | B4: Sample table | C4: Open page | D4: SS-2026-0001..0005 with status badge, batch, farmer, waybill, date, photo thumb | E4: S2
A5: TC-DCOC-04 | B5: Photo & certificate links | C5: Click photo / certificate on Green sample | D5: Photo opens; lab PDF opens in new tab | E5: S2
A6: TC-DCOC-05 | B6: Evidence lock - no photo | C6: Create sample without photo | D6: Blocked; 'geotagged field photo must be attached...' | E6: S1
A7: TC-DCOC-06 | B7: Log field sample (happy) | C7: Upload photo -> create sample with batch | D7: Photo uploads; sample = Yellow-Sampled; new SS code | E7: S1
A8: TC-DCOC-07 | B8: Geo verify - inside boundary | C8: Upload photo GPS inside plot | D8: Badge 'Verified Location' (green) | E8: S2
A9: TC-DCOC-08 | B9: Geo verify - outside boundary | C9: Upload photo GPS outside plot | D9: Flagged 'Boundary Mismatch'; admin audit alert raised | E9: S1

Sheet Lab + Gate3
A1: Test ID | B1: Test | C1: Steps | D1: Expected Result | E1: Severity | F1: Status | G1: Tester | H1: Date | I1: Defect ID | J1: Comments
A2: TC-LAB-01 | B2: Queue renders | C2: Login lab, open /lab | D2: Sample Queue + Completed table with C-org, H/C, heavy-metals | E2: S1
A3: TC-LAB-02 | B3: Log receipt (->Orange) | C3: 'sampled' row -> Log Receipt -> waybill | D3: Advances to lab_received | E3: S1
A4: TC-LAB-03 | B4: Evidence lock - no waybill | C4: Log Receipt blank waybill | D4: Blocked; 'waybill / tracking number is required...' | E4: S2
A5: TC-LAB-04 | B5: Evidence lock - no PDF | C5: Enter Results without certificate | D5: Blocked; 'lab certificate PDF must be attached...' | E5: S1
A6: TC-LAB-05 | B6: Enter results (Green PASS) | C6: Upload PDF, C-org 75, H:C 0.45, metals Pass | D6: Success 'verified (Green)'; batch becomes issuance-eligible | E6: S1
A7: TC-LAB-06 | B7: GATE 3 - high H:C | C7: Enter Results H:C 0.82, metals Pass | D7: Saved but CRITICAL 'permanently locked'; sample=Rejected; batch locked | E7: S1
A8: TC-LAB-07 | B8: GATE 3 - heavy metals fail | C8: Enter Results H:C 0.4, metals Fail | D8: Rejected + locked (as TC-LAB-06) | E8: S1
A9: TC-LAB-08 | B9: Results immutable | C9: Enter results again on completed sample | D9: 409 'results already entered / immutable' | E9: S2
A10: TC-LAB-09 | B10: Order enforced | C10: Enter Results on 'sampled' (not received) | D10: 422 must be received first | E10: S2
A11: TC-LAB-10 | B11: Rejected batch propagation | C11: After TC-LAB-06 open Biochar & Ledger | D11: Batch Rejected + not eligible; Ledger creditable=0 | E11: S1

Sheet Camera Log
A1: Test ID | B1: Test | C1: Steps | D1: Expected Result | E1: Severity | F1: Status | G1: Tester | H1: Date | I1: Defect ID | J1: Comments
A2: TC-CAM-01 | B2: Grid renders | C2: Open /dmrv/camera-log | D2: Photo cards in responsive grid; images load | E2: S2
A3: TC-CAM-02 | B3: Required metadata | C3: Inspect each card | D3: UTC timestamp, GPS to exactly 5 decimals, Device ID | E3: S1
A4: TC-CAM-03 | B4: Filter pills | C4: All/Verified/Flagged/Pending | D4: Grid filters; seeded flagged photo under 'Flagged' | E4: S3
A5: TC-CAM-04 | B5: Verification badges | C5: Inspect cards | D5: Verified=green, Boundary Mismatch=red, Pending=gray | E5: S3

Sheet Yield + Gate2
A1: Test ID | B1: Test | C1: Steps | D1: Expected Result | E1: Severity | F1: Status | G1: Tester | H1: Date | I1: Defect ID | J1: Comments
A2: TC-YIELD-01 | B2: Summary + chart | C2: Open /dmrv/harvest | D2: Per region+crop plots, tonnes, Yield %, flagged; project vs control bar chart | E2: S2
A3: TC-YIELD-02 | B3: Yield calc sanity | C3: Compare Limpopo/Maize row | D3: % ~= (avg project dry - avg control dry)/control x100 | E3: S2
A4: TC-YIELD-03 | B4: Record harvest (in-season) | C4: Limpopo Maize, in-window date, project | D4: 201; row not flagged | E4: S1
A5: TC-YIELD-04 | B5: GATE 2 - out of season | C5: Limpopo Maize, date 2026-10-15 (>30d past) | D5: Saved but amber '...Gold Standard VVB notification logged'; flagged | E5: S1
A6: TC-YIELD-05 | B6: Gate 2 - wrong crop | C6: Limpopo Tobacco, in-window | D6: Saved but flagged | E6: S2
A7: TC-YIELD-06 | B7: Moisture normalisation | C7: Two harvests same wet weight, diff moisture | D7: Yield % uses dry weight | E7: S3

Sheet Seasonality
A1: Test ID | B1: Test | C1: Steps | D1: Expected Result | E1: Severity | F1: Status | G1: Tester | H1: Date | I1: Defect ID | J1: Comments
A2: TC-SEA-01 | B2: Plans table | C2: Open /dmrv/seasonality | D2: Region, crop, year, planned vs actual, window; variance badge if >14d | E2: S3
A3: TC-SEA-02 | B3: Add plan (admin) | C3: Admin -> Add Plan -> save | D3: New plan row; used by Gate 2 | E3: S2
A4: TC-SEA-03 | B4: Window validation | C4: windowEnd before windowStart | D4: 422 'window end must be after start' | E4: S3
A5: TC-SEA-04 | B5: Set actual date | C5: Admin sets actual planting date | D5: Persists; variance recalculates | E5: S3
A6: TC-SEA-05 | B6: Officer cannot add | C6: Login officer, open Seasonality | D6: Read-only (Add hidden) or 403 on API | E6: S2

Sheet Ledger
A1: Test ID | B1: Test | C1: Steps | D1: Expected Result | E1: Severity | F1: Status | G1: Tester | H1: Date | I1: Defect ID | J1: Comments
A2: TC-LEDGER-01 | B2: Formula explainer | C2: Open /dmrv/ledger | D2: Gross=weight x C-org% x 3.67; Deductions=km x diesel; Net=Gross-Deductions | E2: S3
A3: TC-LEDGER-02 | B3: Totals cards | C3: Open page | D3: Gross, Deductions, Net, Creditable + 'N cars off road' | E3: S2
A4: TC-LEDGER-03 | B4: Per-batch math | C4: BC-2026-001 (40t, 78% C-org) | D4: Gross ~= 40 x 0.78 x 3.67 = 114.5t; Net=Gross-deductions | E4: S1
A5: TC-LEDGER-04 | B5: Rejected batch = 0 credit | C5: Find BC-2026-003 (rejected) | D5: Row red; Creditable=0; not eligible | E5: S1
A6: TC-LEDGER-05 | B6: Export CSV | C6: Click Export CSV | D6: CSV downloads; opens in Excel | E6: S3

Sheet Farmer Impact
A1: Test ID | B1: Test | C1: Steps | D1: Expected Result | E1: Severity | F1: Status | G1: Tester | H1: Date | I1: Defect ID | J1: Comments
A2: TC-IMP-01 | B2: Loads own farm | C2: Login farmer, open /impact | D2: Dashboard for own farm (no dropdown) | E2: S1
A3: TC-IMP-02 | B3: Soil Health - pH gauge | C3: Section A | D3: Colour bar Acidic->Alkaline, marker at pH, plain-language advice | E3: S2
A4: TC-IMP-03 | B4: Nutrient (EC) | C4: Inspect | D4: EC value + High/Moderate/Low + 'locked in root zone' note | E4: S3
A5: TC-IMP-04 | B5: Root Room trend | C5: Inspect | D5: Bulk-density line chart + trend arrow (improving if latest<first) | E5: S3
A6: TC-IMP-05 | B6: Water Holding | C6: Inspect | D6: '+X% Water Retention' indicator | E6: S3
A7: TC-IMP-06 | B7: Carbon Bank counter | C7: Section B | D7: Stored CO2e figure; 'N cars off road'; biochar tonnes | E7: S1
A8: TC-IMP-07 | B8: Payout ledger | C8: Inspect | D8: Total Value Earned (R formatted) + payout rows (payment/discount) | E8: S2
A9: TC-IMP-08 | B9: Evidence timeline | C9: Section C | D9: Field-history photos with before/after/sample badges, dates, verified | E9: S2
A10: TC-IMP-09 | B10: Passport QR | C10: Inspect | D10: QR renders; encodes /passport/CSA-2024-00001 | E10: S2
A11: TC-IMP-10 | B11: Data reflects applications | C11: Apply more eligible biochar -> reload | D11: Stored CO2e increased | E11: S2
A12: TC-IMP-11 | B12: Staff pick a farm | C12: Login admin, open /impact | D12: Farmer dropdown; selecting loads that farm | E12: S3
A13: TC-IMP-12 | B13: No profile | C13: Staff w/o farmer profile opens /impact | D13: Friendly 'no farm profile linked'; no crash | E13: S3

Sheet Public Passport
A1: Test ID | B1: Test | C1: Steps | D1: Expected Result | E1: Severity | F1: Status | G1: Tester | H1: Date | I1: Defect ID | J1: Comments
A2: TC-PASS-01 | B2: Public access | C2: Open /passport/CSA-2024-00001 logged-out | D2: Renders without auth | E2: S1
A3: TC-PASS-02 | B3: Content | C3: Inspect | D3: Identity, crops, practices, dMRV stats (CO2e, cars, biochar, verified) | E3: S2
A4: TC-PASS-03 | B4: Methodology badges | C4: Inspect | D4: Verra, Puro.earth, Gold Standard shown | E4: S3
A5: TC-PASS-04 | B5: No financial leakage | C5: Inspect page & network response | D5: No payout/earnings/financial data anywhere | E5: S1
A6: TC-PASS-05 | B6: QR round-trip | C6: Scan QR from TC-IMP-09 with phone | D6: Opens this passport page | E6: S2
A7: TC-PASS-06 | B7: Unknown ID | C7: Open /passport/CSA-0000-99999 | D7: Friendly 'Passport not found' (404) | E7: S3

Sheet Carbon + Offline
A1: Test ID | B1: Test | C1: Steps | D1: Expected Result | E1: Severity | F1: Status | G1: Tester | H1: Date | I1: Defect ID | J1: Comments
A2: TC-CARB-01 | B2: Carbon page loads | C2: Admin -> Carbon Tracking | D2: Trend chart, soil radar, compliance summary, readings table | E2: S2
A3: TC-CARB-02 | B3: Add reading | C3: New reading modal -> save | D3: Row appears; toast | E3: S1
A4: TC-CARB-03 | B4: Sensor/manual toggle | C4: Toggle input method | D4: Method badge reflects choice | E4: S3
A5: TC-CARB-04 | B5: Offline queue | C5: DevTools Offline, submit a reading | D5: 'Saved offline - will sync' toast; entry shows locally | E5: S2
A6: TC-CARB-05 | B6: Sync on reconnect | C6: Go back online | D6: Queued reading syncs (verify via API/refresh) | E6: S2

Sheet Mapping
A1: Test ID | B1: Test | C1: Steps | D1: Expected Result | E1: Severity | F1: Status | G1: Tester | H1: Date | I1: Defect ID | J1: Comments
A2: TC-MAP-01 | B2: Map renders | C2: Admin -> Farm Map | D2: Leaflet map, farm markers, SA extent | E2: S2
A3: TC-MAP-02 | B3: Boundary polygons | C3: Inspect | D3: Farm boundaries as polygons | E3: S3
A4: TC-MAP-03 | B4: Draw boundary | C4: Click-to-draw tool | D4: Polygon draws; area/stats update | E4: S3
A5: TC-MAP-04 | B5: Layer toggle | C5: Street/Satellite/Terrain | D5: Tiles change | E5: S4
A6: TC-MAP-05 | B6: Marker popup | C6: Click a marker | D6: Popup with farmer + coordinates | E6: S3

Sheet LSM
A1: Test ID | B1: Test | C1: Steps | D1: Expected Result | E1: Severity | F1: Status | G1: Tester | H1: Date | I1: Defect ID | J1: Comments
A2: TC-LSM-01 | B2: Scoring tool | C2: LSM Profiles -> answer 6 questions | D2: Auto score + LSM1-LSM5 category | E2: S2
A3: TC-LSM-02 | B3: Category cards | C3: Inspect | D3: LSM1-5 cards with counts, click to expand recommendations | E3: S3
A4: TC-LSM-03 | B4: Charts | C4: Inspect | D4: Pie, province stacked bar, radar breakdown | E4: S4

Sheet Smart Farming
A1: Test ID | B1: Test | C1: Steps | D1: Expected Result | E1: Severity | F1: Status | G1: Tester | H1: Date | I1: Defect ID | J1: Comments
A2: TC-SF-01 | B2: Irrigation | C2: Smart -> Irrigation | D2: Usage charts, schedule table, add modal | E2: S3
A3: TC-SF-02 | B3: Pest & Disease | C3: Smart -> Pest | D3: Outbreak log, severity coding, remedy, resolve, report modal | E3: S3
A4: TC-SF-03 | B4: Weather (mock) | C4: Smart -> Weather (no API key) | D4: Forecast renders with 'mock' badge | E4: S3
A5: TC-SF-04 | B5: Weather (live) | C5: Set VITE_OPENWEATHER_API_KEY, reload | D5: Live data with 'live' badge; province selector works | E5: S3
A6: TC-SF-05 | B6: Inventory CRUD | C6: Smart -> Inventory -> add/edit/delete | D6: Persists (live) or local; low-stock alert on low qty | E6: S2
A7: TC-SF-06 | B7: Financials | C7: Smart -> Financials | D7: Income/expense charts, projection, record modal | E7: S3

Sheet Analytics
A1: Test ID | B1: Test | C1: Steps | D1: Expected Result | E1: Severity | F1: Status | G1: Tester | H1: Date | I1: Defect ID | J1: Comments
A2: TC-RPT-01 | B2: Overview | C2: Analytics -> Overview | D2: KPI cards + charts render | E2: S3
A3: TC-RPT-02 | B3: Report builder | C3: Pick template, apply filters, preview | D3: Column list + preview table populate | E3: S2
A4: TC-RPT-03 | B4: PDF export | C4: Export PDF | D4: Branded PDF downloads, opens, paginated | E4: S2
A5: TC-RPT-04 | B5: CSV export | C5: Export CSV | D5: Valid CSV, opens in Excel | E5: S2
A6: TC-RPT-05 | B6: XLS export | C6: Export XLS | D6: Valid .xlsx with column widths | E6: S2

Sheet Audit Log
A1: Test ID | B1: Test | C1: Steps | D1: Expected Result | E1: Severity | F1: Status | G1: Tester | H1: Date | I1: Defect ID | J1: Comments
A2: TC-AUD-01 | B2: Log renders (admin) | C2: Admin -> Audit Log | D2: Event table (user, role, action, resource, IP, duration, status); 'Live data' | E2: S2
A3: TC-AUD-02 | B3: Persistence | C3: Perform actions, restart backend, reopen | D3: Prior entries still present (DB-persisted) | E3: S1
A4: TC-AUD-03 | B4: Auditor read access | C4: Login auditor -> Audit Log | D4: Can view full trail | E4: S2
A5: TC-AUD-04 | B5: Filters | C5: Filter by action/role, search | D5: Table filters correctly | E5: S3

Sheet Non-Functional
A1: Test ID | B1: Test | C1: Steps | D1: Expected Result | E1: Severity | F1: Status | G1: Tester | H1: Date | I1: Defect ID | J1: Comments
A2: TC-NFR-01 | B2: GDPR banner | C2: First visit (clear localStorage) | D2: Cookie consent banner; choices persist after reload | E2: S3
A3: TC-NFR-02 | B3: i18n | C3: Settings -> Platform -> change language | D3: UI strings switch live | E3: S3
A4: TC-NFR-03 | B4: Responsive | C4: Resize to mobile on key pages | D4: Sidebar overlay; layout reflows; no horizontal scroll | E4: S2
A5: TC-NFR-04 | B5: PWA/offline shell | C5: Load app, go offline, navigate | D5: Cached shell loads; offline indicator shows | E5: S3
A6: TC-NFR-05 | B6: Cross-browser | C6: Smoke path in Chrome/Firefox/Safari/Edge | D6: Consistent rendering & behaviour | E6: S2
A7: TC-NFR-06 | B7: Console clean | C7: Full happy-path with DevTools open | D7: No uncaught console errors | E7: S2
A8: TC-NFR-07 | B8: Security headers | C8: Inspect a response | D8: Helmet headers present; CORS limited to client origin | E8: S3
A9: TC-NFR-08 | B9: No secrets in client | C9: Search built bundle / network | D9: No JWT secret / server-only keys exposed | E9: S2
A10: TC-NFR-09 | B10: Perf sanity | C10: Load dashboard, dMRV pages | D10: Interactive within a few seconds on normal connection | E10: S3

Sheet E2E Scenario
A1: Test ID | B1: Test | C1: Steps | D1: Expected Result | E1: Severity | F1: Status | G1: Tester | H1: Date | I1: Defect ID | J1: Comments
A2: TC-E2E-01 | B2: Officer logs batch 520C | C2: Production log rice husk 30t 520C | D2: Batch created, dCoC=Produced (Gate 1 pass) | E2: S1
A3: TC-E2E-02 | B3: Officer batch 300C | C3: Second batch at 300C | D3: Rejected (Gate 1 blocked) | E3: S1
A4: TC-E2E-03 | B4: Upload photo inside boundary | C4: Geotagged field photo inside plot | D4: Verified | E4: S1
A5: TC-E2E-04 | B5: Log soil sample | C5: Sample from that photo | D5: Yellow (Sampled) | E5: S1
A6: TC-E2E-05 | B6: Lab log receipt | C6: Lab logs receipt with waybill | D6: Orange (Lab Received) | E6: S1
A7: TC-E2E-06 | B7: Lab enter results | C7: PDF, H:C 0.45, metals Pass | D7: Green; batch issuance-eligible | E7: S1
A8: TC-E2E-07 | B8: Shipments + application | C8: Officer ships + applies to farmer | D8: Mass balance updates; over-ship blocked | E8: S1
A9: TC-E2E-08 | B9: Record harvests | C9: In-season + out-of-season | D9: In-season OK; out-of-season flagged (Gate 2) | E9: S1
A10: TC-E2E-09 | B10: Ledger + payout | C10: Admin opens Ledger, records payout | D10: Gross/Net/Creditable shown; payout saved | E10: S1
A11: TC-E2E-10 | B11: Farmer impact | C11: Farmer opens My Farm Impact | D11: Stored CO2e, payout, evidence, passport QR | E11: S1
A12: TC-E2E-11 | B12: Public passport | C12: Open passport logged out | D12: Verified page, no financials | E12: S1
A13: TC-E2E-12 | B13: Auditor read-only | C13: Auditor logs in | D13: Reads all dMRV + audit; cannot edit | E13: S1
A14: TC-E2E-13 | B14: Audit survives restart | C14: Restart backend, reopen Audit Log | D14: All events still present | E14: S1
